LICENSE
README.md
setup.py
az_sights/__init__.py
az_sights.egg-info/PKG-INFO
az_sights.egg-info/SOURCES.txt
az_sights.egg-info/dependency_links.txt
az_sights.egg-info/not-zip-safe
az_sights.egg-info/top_level.txt
tests/__init__.py
tests/test.py